cur/__init__.py
cur/cur.py
cur-0.0.2.dist-info/LICENSE.txt
cur-0.0.2.dist-info/METADATA
cur-0.0.2.dist-info/WHEEL
cur-0.0.2.dist-info/top_level.txt
cur-0.0.2.dist-info/RECORD
