Metadata-Version: 2.1
Name: cur
Version: 0.0.2
Summary: CUR Decomposition
Home-page: https://github.com/blester125/CUR_Decomposition
Download-URL: https://github.com/blester125/CUR_Decomposition/archive/0.0.2.tar.gz
Author: blester125
Author-email: blester125@gmail.com
License: MIT
Platform: UNKNOWN
Classifier: Environment :: Console
Classifier: Development Status :: 3 - Alpha
Classifier: Natural Language :: English
Classifier: Intended Audience :: Developers
Classifier: Intended Audience :: Science/Research
Classifier: Programming Language :: Python :: 3 :: Only
Classifier: Topic :: Scientific/Engineering
Classifier: License :: OSI Approved :: MIT License
Requires-Python: >=3.6
License-File: LICENSE.txt
Requires-Dist: numpy
Provides-Extra: test
Requires-Dist: pytest ; extra == 'test'
